Metadata-Version: 2.1
Name: covidtrackershubraj
Version: 1.0.3
Summary: Commandline Covid-19 Tracker
Home-page: https://github.com/shubraj/covidTracker
Author: Shub Raj Lama
Author-email: me@shubraj.com
License: UNKNOWN
Keywords: covidtracker
Platform: UNKNOWN
Classifier: Programming Language :: Python :: 3
Classifier: License :: OSI Approved :: MIT License
Classifier: Operating System :: OS Independent
Requires-Python: >=3.6
